mspyteams/__init__.py
mspyteams/aiohttp.py
mspyteams/card.py
mspyteams-0.0.2.dist-info/LICENSE
mspyteams-0.0.2.dist-info/WHEEL
mspyteams-0.0.2.dist-info/METADATA
mspyteams-0.0.2.dist-info/RECORD
