Metadata-Version: 2.1
Name: mspyteams
Version: 0.0.2
Summary: Sansio MsTeams cards composing library
Home-page: https://github.com/sander76/mspyteams
License: UNKNOWN
Author: Sander Teunissen
Author-email: no_mail@nomail.com
Requires-Python: >=3.6
Classifier: License :: OSI Approved :: MIT License
Classifier: Programming Language :: Python :: 3 :: Only
Classifier: Programming Language :: Python :: 3.6
Classifier: Programming Language :: Python :: 3.7
Classifier: Programming Language :: Python :: 3.8
Requires-Dist: aiohttp ; extra == "aiohttp"
Requires-Dist: aiohttp ; extra == "dev"
Requires-Dist: pytest-cov ; extra == "dev"
Requires-Dist: pylint ; extra == "dev"
Requires-Dist: coverage[toml]>=5.0.3 ; extra == "dev"
Requires-Dist: pre-commit ; extra == "dev"
Requires-Dist: pytest ; extra == "test"
Requires-Dist: pytest-asyncio ; extra == "test"
Requires-Dist: pytest-aiohttp ; extra == "test"
Provides-Extra: aiohttp
Provides-Extra: dev
Provides-Extra: test
